{

   "details": [
       {
			"Experiment": "Detection of SA1 Fault in JK flip flop",
			"Lab": "Design of Digital System Lab",
			"Discipline": "Computer Science Engineering",
			"Technology": "HTML, Javascript, CSS"
       }
   ],

   "developer": [
       {
      "Developer": "Dr. BISWAJIT R. BHOWMIK",
      "Institute": "National Institute of Technology Karnataka, Surathkal",
      "InstituteAcronym": "NITK"
       }
   ],

   "contributer": [
       {
			"Contributer": "Ullas S",
      "Institute": "National Institute of Technology Karnataka, Surathkal",
      "InstituteAcronym": "NITK"
       },

       {
			"Contributer": "Vanga Kanishka Nandh",
      "Institute": "National Institute of Technology Karnataka, Surathkal",
      "InstituteAcronym": "NITK"
       },

       {
			"Contributer": "Rahul Singh",
      "Institute": "National Institute of Technology Karnataka, Surathkal",
      "InstituteAcronym": "NITK"
       }
   ]

}
